[{"board":{"type":"PolygonGeneratorBoard","generator":"Cairo Pentagonal","parameters":{"squareRegion":false,"width":21,"height":22}},"faceData":".232...0.1..12.3.12....322..33.1.1...1..0.2...3..43.....41.2....2....4.11.2...3...1.2..1.2..4.2.3....0.223...2.4.3..2...3....41......0..24..24.2.....0...2..3.02.1.2...13...12..22....01..2.1..2222.....1.......2..2..24..2...4.4......31......34..1412.32..4...3...33.2.32.3...3133..24.3....24.3....33.2221.22233..1....231.12.......12..2.3..3...1....24...3.4.24421..2..2.0..3.4..3...3..4....23","edgeDifficulty":null,"edgeColorDifficulty":null,"edgeColorSectorDifficulty":null,"fullDifficulty":20.53323534635762}]