[{"board":{"type":"PolygonGeneratorBoard","generator":"Snub Hexagonal","parameters":{"squareRegion":false,"width":9,"height":9}},"faceData":".1.22......22...1.21.....212...0221..10...2.10.1..4..222......021122.....1...1............2","edgeDifficulty":5.073516206919156,"edgeColorDifficulty":4.854560420429879,"edgeColorSectorDifficulty":4.839744873452041,"fullDifficulty":4.839744873452041},{"board":{"type":"PolygonGeneratorBoard","generator":"Snub Hexagonal","parameters":{"squareRegion":false,"width":9,"height":9}},"faceData":".2.1..0.2.011...1..4.0.01...0..1.210..12.....10......012..101.0.......1.40...1.2.....2.1.2.","edgeDifficulty":6.4195358095702755,"edgeColorDifficulty":6.3195958189092485,"edgeColorSectorDifficulty":5.9253627928421055,"fullDifficulty":5.9253627928421055},{"board":{"type":"PolygonGeneratorBoard","generator":"Snub Hexagonal","parameters":{"squareRegion":false,"width":9,"height":9}},"faceData":"12...0...2....2....211..1.1.11...11..12......2201..2.2...01..0.1..0212.1..1.2.1.12.2.22...2","edgeDifficulty":4.85352741464526,"edgeColorDifficulty":4.310895897177864,"edgeColorSectorDifficulty":4.084300921720264,"fullDifficulty":4.084300921720264},{"board":{"type":"PolygonGeneratorBoard","generator":"Snub Hexagonal","parameters":{"squareRegion":false,"width":9,"height":9}},"faceData":".2.111.2..3..2.020.2.2.1..121..2..121..1.21.0..1.211.01...2...1...2.2...2....0.21...22..1.2","edgeDifficulty":5.028465490750089,"edgeColorDifficulty":4.649645796932939,"edgeColorSectorDifficulty":4.524866066978025,"fullDifficulty":4.524866066978025},{"board":{"type":"PolygonGeneratorBoard","generator":"Snub Hexagonal","parameters":{"squareRegion":false,"width":9,"height":9}},"faceData":"....0...1....2.........2..1.2..2321..1.2.1.1....22..2..1..1...032.2.....31........1....02.2","edgeDifficulty":5.236132773894302,"edgeColorDifficulty":4.8009465814118215,"edgeColorSectorDifficulty":4.676366215491935,"fullDifficulty":4.676366215491935},{"board":{"type":"PolygonGeneratorBoard","generator":"Snub Hexagonal","parameters":{"squareRegion":false,"width":9,"height":9}},"faceData":".2..1.11121.221....4....0....0.15....1.1..1.1...12111......01124.1.....2...1122.22...2....2","edgeDifficulty":5.1189709415893185,"edgeColorDifficulty":4.632591576426611,"edgeColorSectorDifficulty":4.1350428585357575,"fullDifficulty":4.1350428585357575}]